[{
	"title":"Bom dia",
	"content":[
		{"audience":"first","senha":"bom dia","zin":"goedemorgen"},
		{"audience":"first","senha":"boa tarde","zin":"goedemiddag"},
		{"audience":"first","senha":"boa noite","zin":"goedenavond"},
		{"audience":"second","senha":"olá","zin":"hallo"},
		{"audience":"second","senha":"oi","zin":"hi"},
		{"audience":"first","senha":"Como você está?","zin":"Hoe gaat het met u?"},
		{"audience":"second","senha":"vai bem, e com você?","zin":"het gaat goed, en met jou?"},
		{"audience":"first","senha":"bem","zin":"goed"},
		{"audience":"first","senha":"Que horas são agora?","zin":"Hoe laat is het nu?"},
		{"audience":"second","senha":"Agora são duas","zin":"Het is nu twee uur"},
		{"audience":"second","senha":"Agora são duas e quinze","zin":"Het is nu kwart over twee"},
		{"audience":"second","senha":"Agora são duas e meia","zin":"Het is nu half drie"},
		{"audience":"second","senha":"Agora são quinze até duas","zin":"Het is nu kwart voor twee"},
		{"audience":"first","senha":"Que dia é hoje?","zin":"Welke dag is het vandaag?"},
		{"audience":"second","senha":"Hoje é quarta","zin":"Het is vandaag woensdag"},
		{"audience":"first","senha":"Qual mês é agora?","zin":"Welke maand is het nu?"},
		{"audience":"second","senha":"Agora é novembro","zin":"Het is nu november"},
		{"audience":"first","senha":"Obrigado, até logo","zin":"Bedankt, tot snel"},
		{"audience":"second","senha":"ciao","zin":"doei"}
	]
},{
	"title":"Você",
	"content":[
		{"audience":"first","senha":"A que horas você vai dormir?","zin":"Hoe laat gaat u 's avonds naar bed?"},
		{"audience":"second","senha":"En vou dormir ás 10","zin":"Ik ga om tien uur naar bed"},
		{"audience":"first","senha":"A que horas você vai acordar de manha?","zin":"Hoe laat wordt u 's ochtends wakker?"},
		{"audience":"second","senha":"Eu acordo ás nove da manha","zin":"Ik word 's ochtends om negen uur wakker"},
		{"audience":"first","senha":"Em que país você nasceu?","zin":"In welk land bent u geboren?"},
		{"audience":"second","senha":"Eu nasci no Brasil","zin":"Ik ben geboren in Brazilië"},
		{"audience":"first","senha":"Qual música você gosta de ouvir?","zin":"Naar welke muziek luistert u graag?"},
		{"audience":"second","senha":"Eu gosto de ouvir forró","zin":"Ik luister graag naar forró"},
		{"audience":"first","senha":"Qual música você gosta?","zin":"Van welke muziek houdt u?"},
		{"audience":"second","senha":"Eu gosto de forró","zin":"Ik hou van forró"},
		{"audience":"first","senha":"Onde você nasceu?","zin":"Waar bent u geboren?"},
		{"audience":"second","senha":"Eu nasci no Brasil","zin":"Ik ben geboren in Brazilië"},
		{"audience":"first","senha":"Quando você nasceu?","zin":"Wanneer bent u geboren?"},
		{"audience":"second","senha":"Eu nasci em 1985","zin":"Ik ben geboren in negentien vijf en tachtig"},
		{"audience":"first","senha":"O que você faz no final de semana?","zin":"Wat doet u in het weekend?"},
		{"audience":"second","senha":"No final de semana eu fico em casa","zin":"In het weekend blijf ik thuis"},
		{"audience":"second","senha":"No final de semana eu vou shopping","zin":"In het weekend ga ik winkelen"},
		{"audience":"first","senha":"O que você faz no seu tempo livre?","zin":"Wat doet u in uw vrije tijd?"},
		{"audience":"second","senha":"No meu tempo livre eu practico esporte","zin":"In mijn vrije tijd sport ik"},
		{"audience":"first","senha":"O que você faz em um feriado público?","zin":"Wat doet u op een feestdag?"},
		{"audience":"second","senha":"Num feriado eu trabalho","zin":"Op een feestdag werk ik"},
		{"audience":"first","senha":"O que você fará amanhã?","zin":"Wat gaat u morgen doen?"},
		{"audience":"second","senha":"amanha eu vou trabalhar","zin":"Morgen ga ik werken"},
		{"audience":"first","senha":"O que você fez ontem?","zin":"Wat hebt u gisteren gedaan?"},
		{"audience":"second","senha":"Ontem eu trabalhei","zin":"Gisteren heb ik gewerkt"},
		{"audience":"first","senha":"O que você acha da Holanda?","zin":"Wat vindt u van Nederland?"},
		{"audience":"second","senha":"Eu acho Holanda é linda","zin":"Ik vind Nederland mooi"},
		{"audience":"first","senha":"O que você acha dos holandeses?","zin":"Wat vindt u van Nederlanders?"},
		{"audience":"second","senha":"Holandeses são um pouco sério","zin":"Nederlanders zijn een beetje serieus"},
		{"audience":"first","senha":"Que tipo de roupa você usa com frequência?","zin":"Wat voor kleren draagt u vaak?"},
		{"audience":"second","senha":"Eu uso calcas e camisas com frequencia","zin":"Ik draag vaak broeken en shirts"},
		{"audience":"first","senha":"Que tipo de roupa você gosta?","zin":"Wat voor kleren vindt u mooi?"},
		{"audience":"second","senha":"Eu gosto das roupas confortaveis","zin":"Ik vind comfortabele kleren mooi"},
		{"audience":"first","senha":"De quais animais você gosta?","zin":"Welke dieren vindt u leuk?"},
		{"audience":"second","senha":"Eu gosto dos gatos","zin":"Ik vind katten leuk"},
		{"audience":"first","senha":"Qual cor você gosta?","zin":"Welke kleur vindt u mooi?"},
		{"audience":"second","senha":"Eu gosto de preto","zin":"Ik vind zwart mooi"}
	]
},{
	"title":"Morar",
	"content":[
		{"audience":"first","senha":"Com quem você vai morar na Holanda?","zin":"Bij wie gaat u wonen in Nederland?"},
		{"audience":"second","senha":"Eu vou morar com meu namorado","zin":"Ik ga bij mijn vriend(je) wonen"},
		{"audience":"first","senha":"Como você chegou aqui?","zin":"Hoe bent u hier gekomen?"},
		{"audience":"second","senha":"Cheguei aqui com aviao","zin":"Ik ben hier met het vliegtuig gekomen"},
		{"audience":"second","senha":"Com aviao","zin":"Met het vliegtuig"},
		{"audience":"first","senha":"Com que frequência você esteve na Holanda?","zin":"Hoe vaak bent u al in Nederland geweest?"},
		{"audience":"second","senha":"Eu já estivo na Holanda três vezes","zin":"Ik ben al drie keer in Nederland geweest"},
		{"audience":"second","senha":"Já três vezes","zin":"Al drie keer"},
		{"audience":"first","senha":"Em que tipo de casa você vai morar na Holanda?","zin":"In wat voor huis gaat u wonen in Nederland?"},
		{"audience":"second","senha":"Eu vou morar numa apartemento","zin":"Ik ga in een apartement wonen"},
		{"audience":"first","senha":"Em que lugar você vai morar na Holanda?","zin":"In welke plaats gaat u wonen in Nederland?"},
		{"audience":"second","senha":"Eu vou morar em Amsterdam","zin":"Ik ga in Amsterdam wonen"},
		{"audience":"second","senha":"Em Amsterdam","zin":"In Amsterdam"},
		{"audience":"first","senha":"Onde você mora?","zin":"Waar woont u?"},
		{"audience":"second","senha":"Moro no Salvador","zin":"Ik woon in Salvador"},
		{"audience":"first","senha":"Com que frequência você assiste TV?","zin":"Hoe vaak kijkt u tv?"},
		{"audience":"second","senha":"As vezes","zin":"Af en toe"},
		{"audience":"first","senha":"Quantas vezes você escuta rádio?","zin":"Hoe vaak luistert u naar de radio?"},
		{"audience":"second","senha":"Eu não escuto rádio","zin":"Ik luister geen radio"},
		{"audience":"second","senha":"Nunca","zin":"Nooit"},
		{"audience":"first","senha":"Qual é o seu endereço?","zin":"Wat is uw adres?"},
		{"audience":"second","senha":"Eu não dou meu endereço","zin":"Ik geef mijn adres niet"},
		{"audience":"first","senha":"Qual é o seu número de telefone?","zin":"Wat is uw telefoonnummer?"},
		{"audience":"second","senha":"Eu não dou meu número de telefone","zin":"Ik geef mijn telefoonnummer niet"},
		{"audience":"first","senha":"Quem mora em sua casa?","zin":"Wie wonen bij u in huis?"},
		{"audience":"second","senha":"Meu irmão, minha irma e meu gonhado","zin":"Mijn broer, zus en zwager"}
	]
},{
	"title":"Aprender",
	"content":[
		{"audience":"first","senha":"Muitos anos de escola você teve?","zin":"Hoeveel jaar school hebt u gehad?"},
		{"audience":"second","senha":"Dez anos","zin":"Tien jaar"},
		{"audience":"first","senha":"Quantos idiomas você fala?","zin":"Hoeveel talen spreekt u?"},
		{"audience":"second","senha":"Falo dois idiomas","zin":"Ik spreek twee talen"},
		{"audience":"first","senha":"O que você aprendeu na escola?","zin":"Wat hebt u geleerd op school?"},
		{"audience":"second","senha":"Eu aprendi conhecimento general","zin":"Ik heb algemene kennis geleerd"},
		{"audience":"first","senha":"O que você acha da língua holandesa?","zin":"Wat vindt u van de Nederlandse taal?"},
		{"audience":"second","senha":"Eu acho a língua holandesa dificil","zin":"Ik vind de Nederlandse taal moeilijk"},
		{"audience":"first","senha":"Onde você aprendeu holandês?","zin":"Waar heeft u Nederlands geleerd?"},
		{"audience":"second","senha":"Aprendi holandês em casa","zin":"Ik heb thuis Nederlands geleerd"},
		{"audience":"first","senha":"Por que você quer ir para a Holanda?","zin":"Waarom wilt u naar Nederland?"},
		{"audience":"second","senha":"Eu quero morar com meu namorado","zin":"Ik wil met mijn vriend samenwonen"},
		{"audience":"first","senha":"Quando você quer ir para a Holanda?","zin":"Wanneer wilt u naar Nederland gaan?"},
		{"audience":"second","senha":"Logo","zin":"Snel"},
		{"audience":"first","senha":"O que você gostaria de aprender na Holanda?","zin":"Wat wilt u graag leren in Nederland?"},
		{"audience":"second","senha":"Eu quero aprender trabalhar numa loja","zin":"Ik wil graag leren werken in een winkel"},
		{"audience":"first","senha":"Quais idiomas você conhece?","zin":"Welke talen spreekt u?"},
		{"audience":"second","senha":"Portugues e Holandes","zin":"Portugees en Nederlands"},
		{"audience":"first","senha":"Quem ajuda você a aprender holandês?","zin":"Wie helpt u met Nederlands leren?"},
		{"audience":"second","senha":"Meu namorado me ajuda","zin":"Mijn vriend helpt me"}
	]
},{
	"title":"Trabalho",
	"content":[
		{"audience":"first","senha":"Como você vai no trabalho?","zin":"Hoe gaat u naar uw werk?"},
		{"audience":"second","senha":"Com onibus","zin":"Met de bus"},
		{"audience":"first","senha":"A que horas você começa a trabalhar?","zin":"Hoe laat begint u met werken?"},
		{"audience":"second","senha":"Às 6 horas a noite","zin":"Om zes uur 's avonds"},
		{"audience":"first","senha":"A que horas você para de trabalhar?","zin":"Hoe laat stopt u met werken?"},
		{"audience":"second","senha":"À um hora a noite","zin":"Om één uur 's nachts"},
		{"audience":"first","senha":"Quantos dias por semana você trabalha?","zin":"Hoeveel dagen in de week werkt u?"},
		{"audience":"second","senha":"Eu trabalho seis dias","zin":"Ik werk zes dagen"},
		{"audience":"first","senha":"Com quantas pessoas você trabalha?","zin":"Met hoeveel mensen werkt u?"},
		{"audience":"second","senha":"Trabalho com vinte gentes","zin":"Ik werk met twintig mensen samen"},
		{"audience":"first","senha":"Em que dias você trabalha?","zin":"Op welke dagen werkt u?"},
		{"audience":"second","senha":"Trabalho todo dia, exceto sabado","zin":"Ik werk op alle dagen, behalve zaterdag"},
		{"audience":"first","senha":"Que tipo de trabalho você quer fazer?","zin":"Wat voor werk wilt u doen?"},
		{"audience":"second","senha":"Eu quero ser designer de interiores","zin":"Ik wil binnenhuis architect worden"}
	]
},{
	"title":"Familia",
	"content":[
		{"audience":"first","senha":"Quantos irmãos e irmãs você tem?","zin":"Hoeveel broers en zussen hebt u?"},
		{"audience":"second","senha":"Eu tenho um irmão e dois irmas","zin":"Ik heb een broer en twee zussen"},
		{"audience":"first","senha":"Quantos filhos você tem?","zin":"Hoeveel kinderen hebt u?"},
		{"audience":"second","senha":"Eu não tenho filhos","zin":"Ik heb geen kinderen"},
		{"audience":"first","senha":"Onde sua família mora?","zin":"Waar woont uw familie?"},
		{"audience":"second","senha":"Minha familia mora em Bahia","zin":"Mijn familie woont in Bahia"},
		{"audience":"first","senha":"O que você gosta de fazer com sua família?","zin":"Wat doet u graag met uw familie?"},
		{"audience":"second","senha":"Gosto de jantar juntos","zin":"Ik vind samen eten gezellig"},
		{"audience":"first","senha":"O que você gosta de fazer com seus amigos?","zin":"Wat doet u graag met uw vrienden?"},
		{"audience":"second","senha":"Eu gosto de dancar","zin":"Ik ga graag dansen"}
	]
},{
	"title":"Comer",
	"content":[
		{"audience":"first","senha":"O que você gosta de beber?","zin":"Wat drinkt u graag?"},
		{"audience":"second","senha":"Gosto de café","zin":"Ik vind koffie lekker"},
		{"audience":"first","senha":"O que você come a noite?","zin":"Wat eet u 's avonds?"},
		{"audience":"second","senha":"A noite como feijão","zin":"'S avonds eet ik bonen met rijst"},
		{"audience":"first","senha":"O que você come de manhã?","zin":"Wat eet u 's ochtends?"},
		{"audience":"second","senha":"De manha eu gosto de comer pão","zin":"'S ochtends eet ik graag brood"},
		{"audience":"first","senha":"O que você comeu ontem?","zin":"Wat hebt u gisteren gegeten?"},
		{"audience":"second","senha":"Ontem eu comi feijão","zin":"Gisteren heb ik bonen met rijst gegeten"},
		{"audience":"first","senha":"O que você gosta de cozinhar?","zin":"Wat kookt u graag?"},
		{"audience":"second","senha":"Eu gosto de cozinhar comidas de Brasil","zin":"Ik kook graag Braziliaanse gerechten"}
	]
},{
	"title": "P.1",
	"content":[
		{"audience":"first","senha":"","zin":"De bus rijdt langzaam. Lia wil..."},
		{"audience":"second","senha":"","zin":"naar huis"},
		{"audience":"first","senha":"","zin":"De dochter van Sophia kijkt veel tv. Ze kan beter gaan..."},
		{"audience":"second","senha":"","zin":"slapen"},
		{"audience":"first","senha":"","zin":"De dokter praat met Sofia. De dokter geeft Sofia..."},
		{"audience":"second","senha":"","zin":"advies"},
		{"audience":"first","senha":"","zin":"De familie Wang woont in een leuke straat. Zij wonen naast..."},
		{"audience":"second","senha":"","zin":"een school"},
		{"audience":"first","senha":"","zin":"De kinderen lezen samen. In het boek staat..."},
		{"audience":"second","senha":"","zin":"een verhaal"},
		{"audience":"first","senha":"","zin":"De klas is leeg. Iedereen is..."},
		{"audience":"second","senha":"","zin":"naar huis"},
		{"audience":"first","senha":"","zin":"De koning is op het nieuws. Hij vertelt over..."},
		{"audience":"second","senha":"","zin":"zijn familie"},
		{"audience":"first","senha":"","zin":"De les begint om 11 uur. Hetty gaat..."},
		{"audience":"second","senha":"","zin":"leren"},
		{"audience":"first","senha":"","zin":"’s Avonds doe ik mijn ring af. Ik leg mijn ring altijd..."},
		{"audience":"second","senha":"","zin":"op het nachtkastje"},
		{"audience":"first","senha":"","zin":"Aaliyah pakt eerst een kopje koffie. Daarna gaat ze..."},
		{"audience":"second","senha":"","zin":"naar haar werk"},
		{"audience":"first","senha":"","zin":"Aaron gaat donderdag op reis. Hij vindt dat..."},
		{"audience":"second","senha":"","zin":"leuk"},
		{"audience":"first","senha":"","zin":"Aaron is dokter. Hij werkt..."},
		{"audience":"second","senha":"","zin":"overdag"},
		{"audience":"first","senha":"","zin":"Aaron is schilder. Hij schildert meestal..."},
		{"audience":"second","senha":"","zin":"huizen"},
		{"audience":"first","senha":"","zin":"Abdul stuurt zijn familie elke week een e-mail. Hij schrijft dan over..."},
		{"audience":"second","senha":"","zin":"wat hij deze week heeft gedaan"},
		{"audience":"first","senha":"","zin":"Abel is op school. Hij heeft..."},
		{"audience":"second","senha":"","zin":"les"},
		{"audience":"first","senha":"","zin":"Achmed is klaar met school. Hij gaat..."},
		{"audience":"second","senha":"","zin":"werken"},
		{"audience":"first","senha":"","zin":"Adam is aan het koken. Hij maakt..."},
		{"audience":"second","senha":"","zin":"spaghetti"},
		{"audience":"first","senha":"","zin":"Ahmed brengt zijn zoon naar het vliegveld. Zijn zoon gaat..."},
		{"audience":"second","senha":"","zin":"vliegen"},
		{"audience":"first","senha":"","zin":"Aiden is bij de bakker. Hij wil..."},
		{"audience":"second","senha":"","zin":"brood"},
		{"audience":"first","senha":"","zin":"Alec gaat naar school. Hij wil graag..."},
		{"audience":"second","senha":"","zin":"leren"}
	]
},{
	"title": "P.2",
	"content":[
		{"audience":"first","senha":"","zin":"Alex gaat altijd met de trein. Ik ga graag met..."},
		{"audience":"second","senha":"","zin":"de fiets"},
		{"audience":"first","senha":"","zin":"Alex is ziek. Hij heeft pijn aan..."},
		{"audience":"second","senha":"","zin":"zijn hoofd"},
		{"audience":"first","senha":"","zin":"Alex wil nieuwe schoenen. Hij gaat naar..."},
		{"audience":"second","senha":"","zin":"de schoenenwinkel"},
		{"audience":"first","senha":"","zin":"Ali kan niet goed lopen. Hij heeft pijn aan zijn..."},
		{"audience":"second","senha":"","zin":"knie"},
		{"audience":"first","senha":"","zin":"Ali werkt in een fabriek. Hij wil..."},
		{"audience":"second","senha":"","zin":"op vakantie"},
		{"audience":"first","senha":"","zin":"Alice werkt in een ziekenhuis. Zij is daar..."},
		{"audience":"second","senha":"","zin":"chirurg"},
		{"audience":"first","senha":"","zin":"Amel sport graag. Sporten is..."},
		{"audience":"second","senha":"","zin":"gezond"},
		{"audience":"first","senha":"","zin":"Ana is niet blij met haar huis. Ze vindt haar huis..."},
		{"audience":"second","senha":"","zin":"klein"},
		{"audience":"first","senha":"","zin":"Ananda is aan het koken. Ze maakt..."},
		{"audience":"second","senha":"","zin":"stamppot"},
		{"audience":"first","senha":"","zin":"Andres werkt op het land. Het werk is..."},
		{"audience":"second","senha":"","zin":"zwaar"},
		{"audience":"first","senha":"","zin":"Anisa maakt huiswerk op de computer. Ze doet dat..."},
		{"audience":"second","senha":"","zin":"iedere dag"},
		{"audience":"first","senha":"","zin":"Anna is bij de dokter. Ze krijgt..."},
		{"audience":"second","senha":"","zin":"een controle"},
		{"audience":"first","senha":"","zin":"Anna’s huis is te klein. Ze wil snel..."},
		{"audience":"second","senha":"","zin":"verhuizen"},
		{"audience":"first","senha":"","zin":"Arif wacht op de bus. De bus komt..."},
		{"audience":"second","senha":"","zin":"snel"},
		{"audience":"first","senha":"","zin":"Arjun moet elke dag reizen naar zijn werk. Hij werkt in..."},
		{"audience":"second","senha":"","zin":"Amsterdam"},
		{"audience":"first","senha":"","zin":"Arnold is schoonmaker. Hij werkt in..."},
		{"audience":"second","senha":"","zin":"kantoren"},
		{"audience":"first","senha":"","zin":"Ayla eet haar ontbijt snel op. Ze heeft..."},
		{"audience":"second","senha":"","zin":"haast"},
		{"audience":"first","senha":"","zin":"Aziz loopt elke dag. Hij loopt naar..."},
		{"audience":"second","senha":"","zin":"huis"},
		{"audience":"first","senha":"","zin":"Barry is geslaagd voor zijn examen. Hij krijgt..."},
		{"audience":"second","senha":"","zin":"een diploma"},
		{"audience":"first","senha":"","zin":"Bart gaat bijna elke dag met de auto. Hij rijdt dan naar..."},
		{"audience":"second","senha":"","zin":"zijn werk"}
	]
},{
	"title": "P.3",
	"content":[
		{"audience":"first","senha":"","zin":"Berat geeft les. Hij vertelt over..."},
		{"audience":"second","senha":"","zin":"de middeleeuwen"},
		{"audience":"first","senha":"","zin":"Bilal gaat naar de bioscoop. Hij gaat met zijn..."},
		{"audience":"second","senha":"","zin":"vriendin"},
		{"audience":"first","senha":"","zin":"Bob houdt niet van zwemmen. Hij gaat liever..."},
		{"audience":"second","senha":"","zin":"lopen"},
		{"audience":"first","senha":"","zin":"Brenda doet een opleiding. Ze moet iedere avond..."},
		{"audience":"second","senha":"","zin":"leren"},
		{"audience":"first","senha":"","zin":"Cai werkt met hout. Hij maakt..."},
		{"audience":"second","senha":"","zin":"meubels"},
		{"audience":"first","senha":"","zin":"Carla drinkt een glas water. Ze doet dat..."},
		{"audience":"second","senha":"","zin":"nu"},
		{"audience":"first","senha":"","zin":"Carlos gaat vroeg slapen. Hij is..."},
		{"audience":"second","senha":"","zin":"moe"},
		{"audience":"first","senha":"","zin":"Carlos is vrij. Hij gaat..."},
		{"audience":"second","senha":"","zin":"dansen"},
		{"audience":"first","senha":"","zin":"Carlos maakt muziek. Hij doet dat..."},
		{"audience":"second","senha":"","zin":"graag"},
		{"audience":"first","senha":"","zin":"Carmen eet elke dag een banaan. Soms eet ze ook..."},
		{"audience":"second","senha":"","zin":"een appel"},
		{"audience":"first","senha":"","zin":"Caro gaat vaak met de bus naar school. Soms gaat ze..."},
		{"audience":"second","senha":"","zin":"lopen"},
		{"audience":"first","senha":"","zin":"Chen verkoopt bloemen. Ze doet dat..."},
		{"audience":"second","senha":"","zin":"iedere dag"},
		{"audience":"first","senha":"","zin":"Chris heeft een computer. Hij gebruikt de computer om te..."},
		{"audience":"second","senha":"","zin":"leren"},
		{"audience":"first","senha":"","zin":"Chris neemt zijn pillen. Hij heeft pijn in zijn..."},
		{"audience":"second","senha":"","zin":"hoofd"},
		{"audience":"first","senha":"","zin":"Christina belt met haar moeder. Ze praten over..."},
		{"audience":"second","senha":"","zin":"hun familie"},
		{"audience":"first","senha":"","zin":"Christo heeft dorst. Hij drinkt een glas..."},
		{"audience":"second","senha":"","zin":"water"},
		{"audience":"first","senha":"","zin":"Claire kijk uit het raam. Ze kijkt naar..."},
		{"audience":"second","senha":"","zin":"buiten"},
		{"audience":"first","senha":"","zin":"Claire leert Nederlands. Ze vindt Nederlands..."},
		{"audience":"second","senha":"","zin":"moeilijk"},
		{"audience":"first","senha":"","zin":"Dael heeft veel geld. Hij werkt..."},
		{"audience":"second","senha":"","zin":"veel"},
		{"audience":"first","senha":"","zin":"Dafne kan goed zingen. Ze kan ook goed..."},
		{"audience":"second","senha":"","zin":"dansen"}
	]
},{
	"title": "P.4",
	"content":[
		{"audience":"first","senha":"","zin":"Daniël heeft pijn aan zijn kies. Hij gaat naar..."},
		{"audience":"second","senha":"","zin":"de dokter"},
		{"audience":"first","senha":"","zin":"Daniëlle gaat studeren. Ze pakt haar..."},
		{"audience":"second","senha":"","zin":"computer"},
		{"audience":"first","senha":"","zin":"Dany heeft hoofdpijn. Ze wil..."},
		{"audience":"second","senha":"","zin":"slapen"},
		{"audience":"first","senha":"","zin":"Dario zit op school. Hij maakt een..."},
		{"audience":"second","senha":"","zin":"toets"},
		{"audience":"first","senha":"","zin":"Dave is niet blij met zijn haar. Zijn haar is..."},
		{"audience":"second","senha":"","zin":"stijl"},
		{"audience":"first","senha":"","zin":"Dave lust geen koffie. Hij drinkt liever..."},
		{"audience":"second","senha":"","zin":"thee"},
		{"audience":"first","senha":"","zin":"Dave werkt in een café. Hij moet daar..."},
		{"audience":"second","senha":"","zin":"bier tappen"},
		{"audience":"first","senha":"","zin":"David en Maria rijden naar de stad. Ze zoeken..."},
		{"audience":"second","senha":"","zin":"een parkeerplaats"},
		{"audience":"first","senha":"","zin":"David heeft een boot. Hij gebruikt de boot om te..."},
		{"audience":"second","senha":"","zin":"varen"},
		{"audience":"first","senha":"","zin":"David is dik. Hij eet elke dag..."},
		{"audience":"second","senha":"","zin":"taart"},
		{"audience":"first","senha":"","zin":"David werkt in een ziekenhuis. Hij is..."},
		{"audience":"second","senha":"","zin":"dokter"},
		{"audience":"first","senha":"","zin":"De auto van Leah is kapot. Ze brengt de auto naar..."},
		{"audience":"second","senha":"","zin":"de garage"},
		{"audience":"first","senha":"","zin":"De baas van Patrick is boos. Patrick vindt dat..."},
		{"audience":"second","senha":"","zin":"niet leuk"},
		{"audience":"first","senha":"","zin":"De broer van Souad heeft een baby gekregen. Souad is..."},
		{"audience":"second","senha":"","zin":"oom"},
		{"audience":"first","senha":"","zin":"De bus is vaak te laat. Paul vindt dat..."},
		{"audience":"second","senha":"","zin":"niet leuk"},
		{"audience":"first","senha":"","zin":"De les is afgelopen. We willen nu..."},
		{"audience":"second","senha":"","zin":"naar huis"},
		{"audience":"first","senha":"","zin":"De man belt in de auto. Dat is..."},
		{"audience":"second","senha":"","zin":"verboden"},
		{"audience":"first","senha":"","zin":"De stoel is kapot. Jaimy gaat de stoel..."},
		{"audience":"second","senha":"","zin":"repareren"},
		{"audience":"first","senha":"","zin":"De trein is vol. Hanna moet..."},
		{"audience":"second","senha":"","zin":"wachten"},
		{"audience":"first","senha":"","zin":"De zoon van Samira gaat naar school. Samira vindt dat..."},
		{"audience":"second","senha":"","zin":"spannend"}
	]
},{
	"title": "P.5",
	"content":[
		{"audience":"first","senha":"","zin":"Debra zit op school. Ze maakt veel..."},
		{"audience":"second","senha":"","zin":"huiswerk"},
		{"audience":"first","senha":"","zin":"Die sinaasappel is oud. Je moet de sinaasappel..."},
		{"audience":"second","senha":"","zin":"opeten"},
		{"audience":"first","senha":"","zin":"Diego houdt van koken. Hij kookt graag voor..."},
		{"audience":"second","senha":"","zin":"zijn ouders"},
		{"audience":"first","senha":"","zin":"Dimitri werkt in een garage. Hij maakt..."},
		{"audience":"second","senha":"","zin":"auto's"},
		{"audience":"first","senha":"","zin":"Dunya gaat naar een feest. Het feest is van haar..."},
		{"audience":"second","senha":"","zin":"vriendin"},
		{"audience":"first","senha":"","zin":"Dylan is bij de tandarts. Dat is..."},
		{"audience":"second","senha":"","zin":"belangrijk"},
		{"audience":"first","senha":"","zin":"Edgar en Joko koken samen. Ze doen dat..."},
		{"audience":"second","senha":"","zin":"iedere zondag"},
		{"audience":"first","senha":"","zin":"Een mug heeft mij geprikt. Nu krijg ik..."},
		{"audience":"second","senha":"","zin":"een bult"},
		{"audience":"first","senha":"","zin":"Ella bakt koekjes. Ze bakt de koekjes voor..."},
		{"audience":"second","senha":"","zin":"haar familie"},
		{"audience":"first","senha":"","zin":"Emma doet een opleiding. Dat is..."},
		{"audience":"second","senha":"","zin":"leuk"},
		{"audience":"first","senha":"","zin":"Emma schrijft alles op. Daarna gaat ze..."},
		{"audience":"second","senha":"","zin":"herhalen"},
		{"audience":"first","senha":"","zin":"Emma wast haar handen. Ze gaat..."},
		{"audience":"second","senha":"","zin":"eten"},
		{"audience":"first","senha":"","zin":"Er is ingebroken bij Ben. Hij belt naar..."},
		{"audience":"second","senha":"","zin":"de politie"},
		{"audience":"first","senha":"","zin":"Er komen nieuwe huizen in onze buurt. Ik vind dat..."},
		{"audience":"second","senha":"","zin":"gezellig"},
		{"audience":"first","senha":"","zin":"Er ligt rommel op straat. Dat is..."},
		{"audience":"second","senha":"","zin":"vies"},
		{"audience":"first","senha":"","zin":"Esma wil lerares worden. Zij gaat..."},
		{"audience":"second","senha":"","zin":"studeren"},
		{"audience":"first","senha":"","zin":"Esra is ziek. Ze vindt dat..."},
		{"audience":"second","senha":"","zin":"niet leuk"},
		{"audience":"first","senha":"","zin":"Fanya is op de markt. Ze zoekt..."},
		{"audience":"second","senha":"","zin":"vis"},
		{"audience":"first","senha":"","zin":"Farid is zanger. Hij moet vandaag..."},
		{"audience":"second","senha":"","zin":"zingen"},
		{"audience":"first","senha":"","zin":"Fausia stapt uit de boot. Ze loopt naar..."},
		{"audience":"second","senha":"","zin":"huis"}
	]
},{
	"title": "P.6",
	"content":[
		{"audience":"first","senha":"","zin":"Felipe houdt van lezen. Hij koopt elke maand..."},
		{"audience":"second","senha":"","zin":"een boek"},
		{"audience":"first","senha":"","zin":"Felix gaat elke dag zwemmen. Soms gaat hij ook..."},
		{"audience":"second","senha":"","zin":"fietsen"},
		{"audience":"first","senha":"","zin":"Fico woont ver van zijn werk. Hij moet elke dag..."},
		{"audience":"second","senha":"","zin":"reizen"},
		{"audience":"first","senha":"","zin":"Filip maakt de badkamer schoon. Hij vindt dat..."},
		{"audience":"second","senha":"","zin":"belangrijk"},
		{"audience":"first","senha":"","zin":"Filiz koopt een nieuwe jas. Ze koopt ook..."},
		{"audience":"second","senha":"","zin":"schoenen"},
		{"audience":"first","senha":"","zin":"Finn kijkt nu televisie. Hij gaat straks..."},
		{"audience":"second","senha":"","zin":"slapen"},
		{"audience":"first","senha":"","zin":"Franco gaat verhuizen. Zijn nieuwe huis heeft een..."},
		{"audience":"second","senha":"","zin":"garage"},
		{"audience":"first","senha":"","zin":"Frank leest de krant. Hij leest over.."},
		{"audience":"second","senha":"","zin":"het nieuws"},
		{"audience":"first","senha":"","zin":"Fred gaat naar school. Hij heeft les tot..."},
		{"audience":"second","senha":"","zin":"vier uur"},
		{"audience":"first","senha":"","zin":"Gabriel maakt een opdracht. Hij doet dat..."},
		{"audience":"second","senha":"","zin":"alleen"},
		{"audience":"first","senha":"","zin":"Gary leest zijn dochter voor. Lezen is..."},
		{"audience":"second","senha":"","zin":"leuk"},
		{"audience":"first","senha":"","zin":"Gary woont bij het strand. Hij wil het liefst..."},
		{"audience":"second","senha":"","zin":"surfen"},
		{"audience":"first","senha":"","zin":"Gina kijkt vaak televisie. Ze houdt van programma's over..."},
		{"audience":"second","senha":"","zin":"dieren"},
		{"audience":"first","senha":"","zin":"Grace houdt niet van groente. Ze vindt dat..."},
		{"audience":"second","senha":"","zin":"vies"},
		{"audience":"first","senha":"","zin":"Halil rijdt in een vrachtwagen. Hij vindt dat..."},
		{"audience":"second","senha":"","zin":"leuk"},
		{"audience":"first","senha":"","zin":"Han heeft zijn diploma gehaald. Hij gaat nu..."},
		{"audience":"second","senha":"","zin":"werken"},
		{"audience":"first","senha":"","zin":"Hannah eet graag vis. Ze haalt die vis..."},
		{"audience":"second","senha":"","zin":"bij de markt"},
		{"audience":"first","senha":"","zin":"Hannah leert Nederlands. Ze leert ook..."},
		{"audience":"second","senha":"","zin":"wiskunde"},
		{"audience":"first","senha":"","zin":"Hannah maakt haar huis schoon. Ze doet dat..."},
		{"audience":"second","senha":"","zin":"iedere week"},
		{"audience":"first","senha":"","zin":"Harold is niet alleen. Hij heeft..."},
		{"audience":"second","senha":"","zin":"vrienden"}
	]
},{
	"title": "P.7",
	"content":[
		{"audience":"first","senha":"","zin":"Harry is gevallen. Hij heeft..."},
		{"audience":"second","senha":"","zin":"pijn"},
		{"audience":"first","senha":"","zin":"Hassan maakt zijn brommer. Het wiel is..."},
		{"audience":"second","senha":"","zin":"stuk"},
		{"audience":"first","senha":"","zin":"Hassan werkt in een restaurant. Hij leert daar..."},
		{"audience":"second","senha":"","zin":"koken"},
		{"audience":"first","senha":"","zin":"Het bord van Sahid is gevallen. Sahid is..."},
		{"audience":"second","senha":"","zin":"verdrietig"},
		{"audience":"first","senha":"","zin":"Het eten is heel warm! Je moet..."},
		{"audience":"second","senha":"","zin":"blazen"},
		{"audience":"first","senha":"","zin":"Het fruit is op. Ik ga nu naar..."},
		{"audience":"second","senha":"","zin":"de supermarkt"},
		{"audience":"first","senha":"","zin":"Het huis van Tania is heel groot. Haar huis heeft..."},
		{"audience":"second","senha":"","zin":"acht kamers"},
		{"audience":"first","senha":"","zin":"Het is donker. Ik reis dan liever niet met..."},
		{"audience":"second","senha":"","zin":"de fiets"},
		{"audience":"first","senha":"","zin":"Het is druk in de stad. Er zijn veel..."},
		{"audience":"second","senha":"","zin":"mensen"},
		{"audience":"first","senha":"","zin":"Het is druk op de weg. Emir vindt dat..."},
		{"audience":"second","senha":"","zin":"eng"},
		{"audience":"first","senha":"","zin":"Het is druk op het station. Er zijn veel..."},
		{"audience":"second","senha":"","zin":"mensen"},
		{"audience":"first","senha":"","zin":"Het is koud in het huis van Faiz. Hij wil..."},
		{"audience":"second","senha":"","zin":"opwarmen"},
		{"audience":"first","senha":"","zin":"Het is slecht weer. Gaan we met de...?"},
		{"audience":"second","senha":"","zin":"auto"},
		{"audience":"first","senha":"","zin":"Het is stil in de klas. De leerlingen..."},
		{"audience":"second","senha":"","zin":"studeren"},
		{"audience":"first","senha":"","zin":"Het is warm vandaag. Ana wil..."},
		{"audience":"second","senha":"","zin":"zwemmen"},
		{"audience":"first","senha":"","zin":"Het is zondag. Eva gaat op zondag altijd naar..."},
		{"audience":"second","senha":"","zin":"de winkel"},
		{"audience":"first","senha":"","zin":"Het regent al de hele dag. William wil..."},
		{"audience":"second","senha":"","zin":"lopen"},
		{"audience":"first","senha":"","zin":"Het regent onderweg. Marta wil..."},
		{"audience":"second","senha":"","zin":"schuilen"},
		{"audience":"first","senha":"","zin":"Het vliegveld is ver weg. We gaan naar het vliegveld met..."},
		{"audience":"second","senha":"","zin":"de trein"},
		{"audience":"first","senha":"","zin":"Hetty is klaar met koken. Ze roept..."},
		{"audience":"second","senha":"","zin":"haar familie"}
	]
},{
	"title": "P.8",
	"content":[
		{"audience":"first","senha":"","zin":"Hue wil naar de markt. Ze gaat..."},
		{"audience":"second","senha":"","zin":"winkelen"},
		{"audience":"first","senha":"","zin":"Ibrahim heeft een kar met spullen. Hij brengt de spullen..."},
		{"audience":"second","senha":"","zin":"naar huis"},
		{"audience":"first","senha":"","zin":"Iedereen is blij. Het is..."},
		{"audience":"second","senha":"","zin":"feest"},
		{"audience":"first","senha":"","zin":"Ik ben op zoek naar het treinstation. Kunt u mij..."},
		{"audience":"second","senha":"","zin":"helpen"},
		{"audience":"first","senha":"","zin":"Ik ben ziek. Ik ga morgen niet..."},
		{"audience":"second","senha":"","zin":"werken"},
		{"audience":"first","senha":"","zin":"Ik drink geen alcohol. Ik drink wel graag..."},
		{"audience":"second","senha":"","zin":"water"},
		{"audience":"first","senha":"","zin":"Ik eet graag brood. Ik houd niet van..."},
		{"audience":"second","senha":"","zin":"kaas"},
		{"audience":"first","senha":"","zin":"Ik eet nooit druiven. Ik vind druiven..."},
		{"audience":"second","senha":"","zin":"vies"},
		{"audience":"first","senha":"","zin":"Ik eet nooit kip. Dat vind ik..."},
		{"audience":"second","senha":"","zin":"vies"},
		{"audience":"first","senha":"","zin":"Ik ga een taart maken. Wil jij...?"},
		{"audience":"second","senha":"","zin":"helpen"},
		{"audience":"first","senha":"","zin":"Ik ga morgen brood kopen. Brood koop ik meestal..."},
		{"audience":"second","senha":"","zin":"vers"},
		{"audience":"first","senha":"","zin":"Ik ga naar de huisarts. Hij geeft mij..."},
		{"audience":"second","senha":"","zin":"advies"},
		{"audience":"first","senha":"","zin":"Ik ga naar mijn zus. Mijn zus woont..."},
		{"audience":"second","senha":"","zin":"in een andere stad"},
		{"audience":"first","senha":"","zin":"Ik ga straks naar Hamza. Hij is..."},
		{"audience":"second","senha":"","zin":"vrij"},
		{"audience":"first","senha":"","zin":"Ik ga vaak met de bus. Ik ga dan naar..."},
		{"audience":"second","senha":"","zin":"school"},
		{"audience":"first","senha":"","zin":"Ik heb deze krant gelezen. Wil jij de krant nu..?"},
		{"audience":"second","senha":"","zin":"lezen"},
		{"audience":"first","senha":"","zin":"Ik heb een computer met internet. Die gebruik ik..."},
		{"audience":"second","senha":"","zin":"vaak"},
		{"audience":"first","senha":"","zin":"Ik heb een nieuwe tafel gekocht. Wil jij mijn oude tafel...?"},
		{"audience":"second","senha":"","zin":"hebben"},
		{"audience":"first","senha":"","zin":"Ik heb geen auto. Een auto is..."},
		{"audience":"second","senha":"","zin":"duur"},
		{"audience":"first","senha":"","zin":"Ik heb soep gemaakt. Wil jij mijn soep...?"},
		{"audience":"second","senha":"","zin":"eten"}
	]
},{
	"title": "P.9",
	"content":[
		{"audience":"first","senha":"","zin":"Ik heb wortels gekocht. Ik koop de wortels voor..."},
		{"audience":"second","senha":"","zin":"het konijn"},
		{"audience":"first","senha":"","zin":"Ik houd van tekenen. Ik teken..."},
		{"audience":"second","senha":"","zin":"een kat"},
		{"audience":"first","senha":"","zin":"Ik lees het nieuws op mijn telefoon. Mijn man leest het nieuws..."},
		{"audience":"second","senha":"","zin":"in de krant"},
		{"audience":"first","senha":"","zin":"Ik lees vaak. Ik lees graag..."},
		{"audience":"second","senha":"","zin":"boeken"},
		{"audience":"first","senha":"","zin":"Ik wil zieke mensen helpen. Ik vind dat..."},
		{"audience":"second","senha":"","zin":"belangrijk"},
		{"audience":"first","senha":"","zin":"Imani vindt school leuk. Zij houdt van..."},
		{"audience":"second","senha":"","zin":"leren"},
		{"audience":"first","senha":"","zin":"In de stad rijden veel brommers. Ik vind dat..."},
		{"audience":"second","senha":"","zin":"gevaarlijk"},
		{"audience":"first","senha":"","zin":"In een grote stad wonen veel mensen. Ik vind dat..."},
		{"audience":"second","senha":"","zin":"gezellig"},
		{"audience":"first","senha":"","zin":"In het eten zitten pepers. Ik vind dat..."},
		{"audience":"second","senha":"","zin":"lekker"},
		{"audience":"first","senha":"","zin":"Inez en Luis bouwen een huis. Het huis heeft nog geen..."},
		{"audience":"second","senha":"","zin":"vloer"},
		{"audience":"first","senha":"","zin":"Inez gaat naar een concert. Ze gaat..."},
		{"audience":"second","senha":"","zin":"dansen"},
		{"audience":"second","senha":"","zin":"uit"},
		{"audience":"first","senha":"","zin":"Is dat boek leuk? Ik wil het boek ook graag..."},
		{"audience":"second","senha":"","zin":"lezen"},
		{"audience":"first","senha":"","zin":"Isa heeft pauze. Ze belt met haar..."},
		{"audience":"second","senha":"","zin":"man"},
		{"audience":"first","senha":"","zin":"Isabel speelt graag met haar pop. Soms speelt ze ook met..."},
		{"audience":"second","senha":"","zin":"haar moeder"},
		{"audience":"first","senha":"","zin":"Ismet heeft groenten in zijn tuin. Hij gaat de groenten..."},
		{"audience":"second","senha":"","zin":"eten"},
		{"audience":"first","senha":"","zin":"Ivan is niet blij met zijn werk. Hij vindt zijn werk te..."},
		{"audience":"second","senha":"","zin":"makkelijk"},
		{"audience":"first","senha":"","zin":"Iwan wil gezond zijn. Hij drinkt geen..."},
		{"audience":"second","senha":"","zin":"frisdrank"},
		{"audience":"first","senha":"","zin":"Jack koopt tomaten. Hij koopt ook..."},
		{"audience":"second","senha":"","zin":"spaghetti"},
		{"audience":"first","senha":"","zin":"Jack wil de muziek niet horen. Hij vindt de muziek..."},
		{"audience":"second","senha":"","zin":"saai"},
		{"audience":"first","senha":"","zin":"Jacques is leraar. Hij geeft..."},
		{"audience":"second","senha":"","zin":"les"}
	]
},{
	"title": "P.10",
	"content":[
		{"audience":"first","senha":"","zin":"Jada maakt pannenkoeken voor haar familie. Zij doet dat..."},
		{"audience":"second","senha":"","zin":"graag"},
		{"audience":"first","senha":"","zin":"Jafar houdt niet van dansen. Hij vindt dansen..."},
		{"audience":"second","senha":"","zin":"moeilijk"},
		{"audience":"first","senha":"","zin":"Jakob zoekt een taxi. Hij wil..."},
		{"audience":"second","senha":"","zin":"naar huis"},
		{"audience":"first","senha":"","zin":"Jamal heeft een nieuwe scooter. Hij kan nu..."},
		{"audience":"second","senha":"","zin":"rijden"},
		{"audience":"first","senha":"","zin":"Jamal woont in een flatgebouw. Hij wil graag..."},
		{"audience":"second","senha":"","zin":"een tuin"},
		{"audience":"first","senha":"","zin":"Jamila maakt kleding. Die kleding is voor..."},
		{"audience":"second","senha":"","zin":"haar familie"},
		{"audience":"first","senha":"","zin":"Jan heeft zijn arm gebroken. Hij moet nu..."},
		{"audience":"second","senha":"","zin":"rusten"},
		{"audience":"first","senha":"","zin":"Janek heeft koorts. Zijn moeder geeft hem..."},
		{"audience":"second","senha":"","zin":"water"},
		{"audience":"first","senha":"","zin":"Janine leert Nederlands. Ze praat met de lerares over..."},
		{"audience":"second","senha":"","zin":"het weer"},
		{"audience":"first","senha":"","zin":"Jara is zwanger. Ze krijgt..."},
		{"audience":"second","senha":"","zin":"een kind"},
		{"audience":"first","senha":"","zin":"Jasmine gaat naar het ziekenhuis. In het ziekenhuis zijn..."},
		{"audience":"second","senha":"","zin":"dokters"},
		{"audience":"first","senha":"","zin":"Jason gaat graag naar school. Hij kan goed..."},
		{"audience":"second","senha":"","zin":"leren"},
		{"audience":"first","senha":"","zin":"Jessie houdt van muziek. Ze speelt graag..."},
		{"audience":"second","senha":"","zin":"piano"},
		{"audience":"first","senha":"","zin":"Jessie moet langer werken vandaag. Ze mag pas om acht uur..."},
		{"audience":"second","senha":"","zin":"naar huis"},
		{"audience":"first","senha":"","zin":"Jie is op de markt. Hij ziet..."},
		{"audience":"second","senha":"","zin":"fruit"},
		{"audience":"first","senha":"","zin":"Jim gaat naar het strand. Het is daar..."},
		{"audience":"second","senha":"","zin":"druk"},
		{"audience":"first","senha":"","zin":"Jim heeft haast. Hij moet snel naar..."},
		{"audience":"second","senha":"","zin":"huis"},
		{"audience":"first","senha":"","zin":"Jing maakt de borden schoon. Daarna gaat ze..."},
		{"audience":"second","senha":"","zin":"spelen"},
		{"audience":"first","senha":"","zin":"Joel heeft een vieze keuken. Hij moet..."},
		{"audience":"second","senha":"","zin":"schoonmaken"},
		{"audience":"first","senha":"","zin":"Johanna doet suiker in haar koffie. Suiker is..."},
		{"audience":"second","senha":"","zin":"zoet"}
	]
},{
	"title": "P.11",
	"content":[
		{"audience":"first","senha":"","zin":"John en zijn dochter bakken samen taart. Ze vinden dat..."},
		{"audience":"second","senha":"","zin":"leuk"},
		{"audience":"first","senha":"","zin":"John houdt van paarden. Hij vindt paarden..."},
		{"audience":"second","senha":"","zin":"mooi"},
		{"audience":"first","senha":"","zin":"John woont bij een bos. Hij gaat daar elk weekend..."},
		{"audience":"second","senha":"","zin":"wandelen"},
		{"audience":"first","senha":"","zin":"Johnny is moe. Hij wil..."},
		{"audience":"second","senha":"","zin":"slapen"},
		{"audience":"first","senha":"","zin":"Johnny is vrij op zaterdag. Hij gaat..."},
		{"audience":"second","senha":"","zin":"rusten"},
		{"audience":"first","senha":"","zin":"Jonas werkt altijd buiten. Dat is..."},
		{"audience":"second","senha":"","zin":"gezond"},
		{"audience":"first","senha":"","zin":"Josh heeft de hele dag gelopen. Hij wil nu..."},
		{"audience":"second","senha":"","zin":"zitten"},
		{"audience":"first","senha":"","zin":"Josh koopt een krant in de winkel. Hij koopt ook..."},
		{"audience":"second","senha":"","zin":"brood"},
		{"audience":"first","senha":"","zin":"Judy leest een tijdschrift. Soms leest ze ook..."},
		{"audience":"second","senha":"","zin":"boeken"},
		{"audience":"first","senha":"","zin":"Julio gaat verhuizen. Hij moet..."},
		{"audience":"second","senha":"","zin":"inpakken"},
		{"audience":"first","senha":"","zin":"Karim heeft pijn in zijn rug. Hij moet..."},
		{"audience":"second","senha":"","zin":"rusten"},
		{"audience":"first","senha":"","zin":"Karim leest het weerbericht. Het weer wordt..."},
		{"audience":"second","senha":"","zin":"zonnig"},
		{"audience":"first","senha":"","zin":"Karima gaat naar de dokter. Ze voelt zich..."},
		{"audience":"second","senha":"","zin":"ziek"},
		{"audience":"first","senha":"","zin":"Karin kijkt naar het journaal. Ze doet dat..."},
		{"audience":"second","senha":"","zin":"iedere dag"},
		{"audience":"first","senha":"","zin":"Karl gaat met zijn dochter naar de dierentuin. Ze kijken naar..."},
		{"audience":"second","senha":"","zin":"dieren"},
		{"audience":"first","senha":"","zin":"Katya volgt een opleiding. Ze wil..."},
		{"audience":"second","senha":"","zin":"dokter worden"},
		{"audience":"first","senha":"","zin":"Kay zoekt een nieuw huis. Hij vindt zijn oude huis..."},
		{"audience":"second","senha":"","zin":"klein"},
		{"audience":"first","senha":"","zin":"Kei eet 's avonds met zijn familie. Dat vindt hij..."},
		{"audience":"second","senha":"","zin":"gezellig"},
		{"audience":"first","senha":"","zin":"Kenji rookt al twintig jaar sigaretten. Dat is..."},
		{"audience":"second","senha":"","zin":"ongezond"},
		{"audience":"first","senha":"","zin":"Kenny zoekt op internet. Hij zoekt naar..."},
		{"audience":"second","senha":"","zin":"familie"}
	]
},{
	"title": "P.12",
	"content":[
		{"audience":"first","senha":"","zin":"Kevin eet een salade met paprika. In de salade zit ook..."},
		{"audience":"second","senha":"","zin":"tomaat"},
		{"audience":"first","senha":"","zin":"Kevin heeft huiswerk. Hij moet veel..."},
		{"audience":"second","senha":"","zin":"leren"},
		{"audience":"first","senha":"","zin":"Kevin werkt in een restaurant. Hij maakt vandaag..."},
		{"audience":"second","senha":"","zin":"het dessert"},
		{"audience":"first","senha":"","zin":"Kevin zit in de klas. Hij heeft een vraag over..."},
		{"audience":"second","senha":"","zin":"de politiek"},
		{"audience":"first","senha":"","zin":"Khalid is visser. Na het werk is hij vaak..."},
		{"audience":"second","senha":"","zin":"moe"},
		{"audience":"first","senha":"","zin":"Kun je mij een lepel geven? Ik wil..."},
		{"audience":"second","senha":"","zin":"eten"},
		{"audience":"first","senha":"","zin":"Kun je mij naar het station brengen. Ik moet op tijd..."},
		{"audience":"second","senha":"","zin":"vertrekken"},
		{"audience":"first","senha":"","zin":"Kwasi is chauffeur. Hij rijdt..."},
		{"audience":"second","senha":"","zin":"iedere dag"},
		{"audience":"first","senha":"","zin":"Laila moet elke dag vroeg opstaan. Soms is ze..."},
		{"audience":"second","senha":"","zin":"moe"},
		{"audience":"first","senha":"","zin":"Laiqa werkt elke dag buiten. Ze houdt van..."},
		{"audience":"second","senha":"","zin":"mensen"},
		{"audience":"first","senha":"","zin":"Laura heeft veel collega's. Ze gaan samen..."},
		{"audience":"second","senha":"","zin":"dansen"},
		{"audience":"first","senha":"","zin":"Lea eet graag in een restaurant. Ze vindt dat..."},
		{"audience":"second","senha":"","zin":"gezellig"},
		{"audience":"first","senha":"","zin":"Lea gaat naar haar kleinzoon. Ze geeft hem..."},
		{"audience":"second","senha":"","zin":"aandacht"},
		{"audience":"first","senha":"","zin":"Lea is in het ziekenhuis. Ze wil..."},
		{"audience":"second","senha":"","zin":"hulp"},
		{"audience":"first","senha":"","zin":"Lei speelt op straat. Dat is..."},
		{"audience":"second","senha":"","zin":"gevaarlijk"},
		{"audience":"second","senha":"","zin":"gezellig"},
		{"audience":"first","senha":"","zin":"Leon is verkouden. Hij moet..."},
		{"audience":"second","senha":"","zin":"niezen"},
		{"audience":"first","senha":"","zin":"Leon speelt gitaar. Hij doet dat..."},
		{"audience":"second","senha":"","zin":"iedere dag"},
		{"audience":"first","senha":"","zin":"Leyla slaapt samen met haar zus in een kamer. Zij vinden dat..."},
		{"audience":"second","senha":"","zin":"gezellig"},
		{"audience":"first","senha":"","zin":"Li en Chen gaan iets drinken. Ze drinken..."},
		{"audience":"second","senha":"","zin":"bier"},
		{"audience":"first","senha":"","zin":"Lia wil meer geld voor haar werk. Dan kan ze..."},
		{"audience":"second","senha":"","zin":"verhuizen"}
	]
},{
	"title": "P.13",
	"content":[
		{"audience":"first","senha":"","zin":"Liam kan niet goed zien. Hij moet..."},
		{"audience":"second","senha":"","zin":"een bril"},
		{"audience":"first","senha":"","zin":"Lily gaat elke dinsdag sporten. Ze eet daarna altijd..."},
		{"audience":"second","senha":"","zin":"gezond"},
		{"audience":"first","senha":"","zin":"Lin zoekt werk. Ze gaat naar..."},
		{"audience":"second","senha":"","zin":"https://www.werkzoeken.nl/"},
		{"audience":"first","senha":"","zin":"Ling wil iets eten. Ze eet liever geen..."},
		{"audience":"second","senha":"","zin":"kaas"},
		{"audience":"first","senha":"","zin":"Linn heeft niet goed geslapen. Ze blijft..."},
		{"audience":"second","senha":"","zin":"wakker"},
		{"audience":"first","senha":"","zin":"Liyen gaat vanavond koken. Ze gaat eerst..."},
		{"audience":"second","senha":"","zin":"boodschappen doen"},
		{"audience":"first","senha":"","zin":"Lizzie en haar moeder gaan met het vliegtuig. Lizzie vindt dat..."},
		{"audience":"second","senha":"","zin":"spannend"},
		{"audience":"first","senha":"","zin":"Louis gaat op de scooter naar zijn werk. Hij doet dat..."},
		{"audience":"second","senha":"","zin":"iedere dag"},
		{"audience":"first","senha":"","zin":"Louis gebruikt de computer. Hij wil..."},
		{"audience":"second","senha":"","zin":"werk zoeken"},
		{"audience":"first","senha":"","zin":"Lucia heeft haar been gebroken. Nu kan ze niet..."},
		{"audience":"second","senha":"","zin":"lopen"},
		{"audience":"first","senha":"","zin":"Lucia wil nieuw werk. Ze vindt haar oude werk..."},
		{"audience":"second","senha":"","zin":"saai"},
		{"audience":"first","senha":"","zin":"Madee heeft een auto. Ze gaat met de auto naar..."},
		{"audience":"second","senha":"","zin":"haar moeder"},
		{"audience":"first","senha":"","zin":"Mae heeft een nieuwe auto. Ze kan nu..."},
		{"audience":"second","senha":"","zin":"rijden"},
		{"audience":"first","senha":"","zin":"Mag ik jouw brommer lenen? Mijn brommer is..."},
		{"audience":"second","senha":"","zin":"stuk"},
		{"audience":"first","senha":"","zin":"Mai kijkt niet naar het nieuws. Ze vindt het nieuws..."},
		{"audience":"second","senha":"","zin":"negatief"},
		{"audience":"first","senha":"","zin":"Maja maakt soep. De soep is..."},
		{"audience":"second","senha":"","zin":"heet"},
		{"audience":"first","senha":"","zin":"Malik gaat vandaag niet sporten. Hij heeft geen..."},
		{"audience":"second","senha":"","zin":"energie"},
		{"audience":"first","senha":"","zin":"Malik heeft een nieuwe bank gekocht. De oude bank was..."},
		{"audience":"second","senha":"","zin":"stuk"},
		{"audience":"first","senha":"","zin":"Mandy eet vaak chips als ze een film kijkt. Ze eet soms ook..."},
		{"audience":"second","senha":"","zin":"fruit"},
		{"audience":"first","senha":"","zin":"Manuel is buschauffeur. Hij rijdt..."},
		{"audience":"second","senha":"","zin":"iedere dag"}
	]
},{
	"title": "P.14",
	"content":[
		{"audience":"first","senha":"","zin":"Marco heeft zin in koffie. Hij wil ook..."},
		{"audience":"second","senha":"","zin":"water"},
		{"audience":"first","senha":"","zin":"Marco is ziek. Hij belt..."},
		{"audience":"second","senha":"","zin":"de dokter"},
		{"audience":"first","senha":"","zin":"Maria heeft griep. Ze moet..."},
		{"audience":"second","senha":"","zin":"rusten"},
		{"audience":"first","senha":"","zin":"Maria kan goed koken. Ze kookt meestal..."},
		{"audience":"second","senha":"","zin":"stamppot"},
		{"audience":"first","senha":"","zin":"Maria leest een boek. Ze vindt het..."},
		{"audience":"second","senha":"","zin":"spannend"},
		{"audience":"first","senha":"","zin":"Maria leest op zondag de krant. Ze leest soms..."},
		{"audience":"second","senha":"","zin":"een boek"},
		{"audience":"first","senha":"","zin":"Mariam praat met de leraar. Mariam praat ook met haar..."},
		{"audience":"second","senha":"","zin":"dochter"},
		{"audience":"first","senha":"","zin":"Martin eet elke ochtend een ei. Zijn vrouw eet meestal..."},
		{"audience":"second","senha":"","zin":"een croissant"},
		{"audience":"first","senha":"","zin":"Martin stelt een vraag aan de docent. De vraag gaat over..."},
		{"audience":"second","senha":"","zin":"het huiswerk"},
		{"audience":"first","senha":"","zin":"Maryam kookt voor Dina. Maryam maakt..."},
		{"audience":"second","senha":"","zin":"stamppot"},
		{"audience":"first","senha":"","zin":"Masha kan vandaag zitten in de bus. Soms moet ze..."},
		{"audience":"second","senha":"","zin":"staan"},
		{"audience":"first","senha":"","zin":"Max draagt een helm op zijn werk. Dat moet van zijn..."},
		{"audience":"second","senha":"","zin":"chef"},
		{"audience":"first","senha":"","zin":"Maya doet de gordijnen dicht. Ze gaat..."},
		{"audience":"second","senha":"","zin":"slapen"},
		{"audience":"first","senha":"","zin":"Megan gaat vandaag verhuizen. Ze woont straks..."},
		{"audience":"second","senha":"","zin":"alleen"},
		{"audience":"first","senha":"","zin":"Melissa wacht op het station. Ze wacht op haar..."},
		{"audience":"second","senha":"","zin":"vriend"},
		{"audience":"first","senha":"","zin":"Mevrouw Perez heeft geen auto meer. Nu moet ze..."},
		{"audience":"second","senha":"","zin":"fietsen"},
		{"audience":"first","senha":"","zin":"Mia maakt zelf kleren. Vandaag maakt ze een..."},
		{"audience":"second","senha":"","zin":"broek"},
		{"audience":"first","senha":"","zin":"Mia moet snel naar huis. Ze gaat met de..."},
		{"audience":"second","senha":"","zin":"auto"},
		{"audience":"first","senha":"","zin":"Michael houdt niet van tennis. Hij houdt meer van..."},
		{"audience":"second","senha":"","zin":"voetbal"},
		{"audience":"first","senha":"","zin":"Michelle kijkt vaak films. Ze houdt van films over..."},
		{"audience":"second","senha":"","zin":"romantiek"}
	]
},{
	"title": "P.15",
	"content":[
		{"audience":"first","senha":"","zin":"Michelle maakt huiswerk. Ze vindt het huiswerk..."},
		{"audience":"second","senha":"","zin":"makkelijk"},
		{"audience":"first","senha":"","zin":"Miguel stopt met werken. Hij is..."},
		{"audience":"second","senha":"","zin":"rijk"},
		{"audience":"second","senha":"","zin":"oud"},
		{"audience":"first","senha":"","zin":"Mijn auto is kapot. Nu moet ik..."},
		{"audience":"second","senha":"","zin":"fietsen"},
		{"audience":"first","senha":"","zin":"Mijn baas fietst elke dag. Ik doe dat..."},
		{"audience":"second","senha":"","zin":"ook"},
		{"audience":"first","senha":"","zin":"Mijn benzine is op. Nu moet ik..."},
		{"audience":"second","senha":"","zin":"tanken"},
		{"audience":"first","senha":"","zin":"Mijn broer houdt niet van varen. Hij wordt altijd ziek op..."},
		{"audience":"second","senha":"","zin":"het water"},
		{"audience":"first","senha":"","zin":"Mijn broer zingt veel. Hij is..."},
		{"audience":"second","senha":"","zin":"zanger"},
		{"audience":"first","senha":"","zin":"Mijn buurman maakt graag muziek. Dat vind ik..."},
		{"audience":"second","senha":"","zin":"prima"},
		{"audience":"first","senha":"","zin":"Mijn opa gaat elke dag wandelen. Dat is..."},
		{"audience":"second","senha":"","zin":"gezond"},
		{"audience":"first","senha":"","zin":"Mijn opa zit op de bank. Hij kijkt naar..."},
		{"audience":"second","senha":"","zin":"buiten"},
		{"audience":"first","senha":"","zin":"Mijn telefoon is kapot. Nu kan ik niet..."},
		{"audience":"second","senha":"","zin":"bellen"},
		{"audience":"first","senha":"","zin":"Mijn trein vertrekt over een half uur. Ik ga nu..."},
		{"audience":"second","senha":"","zin":"wachten"},
		{"audience":"first","senha":"","zin":"Mijn vader heeft een paard. Hij gaat..."},
		{"audience":"second","senha":"","zin":"paardrijden"},
		{"audience":"first","senha":"","zin":"Mijn vader loopt met een stok. Mijn vader is..."},
		{"audience":"second","senha":"","zin":"oud"},
		{"audience":"first","senha":"","zin":"Mijn vader luistert graag naar het nieuws. Hij luistert ook naar..."},
		{"audience":"second","senha":"","zin":"muziek"},
		{"audience":"first","senha":"","zin":"Mijn zus rijdt altijd hard. Ik vind dat..."},
		{"audience":"second","senha":"","zin":"gevaarlijk"},
		{"audience":"first","senha":"","zin":"Mike heeft pijn aan zijn been. Hij heeft ook pijn aan zijn..."},
		{"audience":"second","senha":"","zin":"arm"},
		{"audience":"first","senha":"","zin":"Ming rijdt vaak op zijn scooter. Hij wil niet..."},
		{"audience":"second","senha":"","zin":"lopen"},
		{"audience":"first","senha":"","zin":"Mira heeft zin in koffie. Ze drinkt koffie met..."},
		{"audience":"second","senha":"","zin":"suiker"},
		{"audience":"first","senha":"","zin":"Mo en zijn familie spelen een spel. Daarna gaan ze..."},
		{"audience":"second","senha":"","zin":"slapen"}
	]
},{
	"title": "P.16",
	"content":[
		{"audience":"first","senha":"","zin":"Mo zit aan tafel. Hij schrijft een brief aan zijn..."},
		{"audience":"second","senha":"","zin":"moeder"},
		{"audience":"first","senha":"","zin":"Mohammed maakt auto’s. Dat vindt hij..."},
		{"audience":"second","senha":"","zin":"leuk"},
		{"audience":"first","senha":"","zin":"Monica maakt graag foto's. Ze maakt het liefst foto's van..."},
		{"audience":"second","senha":"","zin":"dieren"},
		{"audience":"first","senha":"","zin":"Monica wil graag een huis met een tuin. Ze vindt dat..."},
		{"audience":"second","senha":"","zin":"gezellig"},
		{"audience":"first","senha":"","zin":"Myra en Liz gaan naar een café. Ze willen graag..."},
		{"audience":"second","senha":"","zin":"praten"},
		{"audience":"first","senha":"","zin":"Nadia heeft kip gekocht. Ze gaat de kip eerst..."},
		{"audience":"second","senha":"","zin":"grillen"},
		{"audience":"first","senha":"","zin":"Naima wil kapper worden. Ze leert..."},
		{"audience":"second","senha":"","zin":"knippen"},
		{"audience":"first","senha":"","zin":"Nancy en Oscar zitten in de bioscoop. Ze vinden de film..."},
		{"audience":"second","senha":"","zin":"spannend"},
		{"audience":"first","senha":"","zin":"Nasir zoekt een nieuw huis. Hij wil een huis met..."},
		{"audience":"second","senha":"","zin":"tuin"},
		{"audience":"first","senha":"","zin":"Nasira woont bij de supermarkt. Ze woont ook bij..."},
		{"audience":"second","senha":"","zin":"de school"},
		{"audience":"first","senha":"","zin":"Nick wil naar zijn familie. Hij reist met..."},
		{"audience":"second","senha":"","zin":"de auto"},
		{"audience":"first","senha":"","zin":"Nick zoekt werk. Hij wil graag werken bij..."},
		{"audience":"second","senha":"","zin":"een winkel"},
		{"audience":"first","senha":"","zin":"Nicole gaat naar de tandarts. Ze heeft pijn aan haar..."},
		{"audience":"second","senha":"","zin":"tand"},
		{"audience":"first","senha":"","zin":"Nikki zoekt een nieuw huis. Ze wil graag..."},
		{"audience":"second","senha":"","zin":"een tuin"},
		{"audience":"first","senha":"","zin":"Nina speelt in de tuin. Ze speelt met..."},
		{"audience":"second","senha":"","zin":"haar broer"},
		{"audience":"first","senha":"","zin":"Noah leest een bericht in de krant. Het bericht gaat over..."},
		{"audience":"second","senha":"","zin":"voetbal"},
		{"audience":"first","senha":"","zin":"Noor werkt in een winkel. Ze verkoopt broeken en ook..."},
		{"audience":"second","senha":"","zin":"tijdschriften"},
		{"audience":"first","senha":"","zin":"Nora en Souffian wonen in een dorp. Ze wonen liever..."},
		{"audience":"second","senha":"","zin":"in een stad"},
		{"audience":"first","senha":"","zin":"Odara ruimt het huis op. Ze legt de kleren..."},
		{"audience":"second","senha":"","zin":"in de kast"},
		{"audience":"first","senha":"","zin":"Olga is ziek. Ze moet..."},
		{"audience":"second","senha":"","zin":"rusten"}
	]
},{
	"title": "P.17",
	"content":[
		{"audience":"first","senha":"","zin":"Omar koopt vis. Hij koopt ook..."},
		{"audience":"second","senha":"","zin":"wijn"},
		{"audience":"first","senha":"","zin":"Omid leest 's ochtends altijd eerst de krant. Daarna gaat hij..."},
		{"audience":"second","senha":"","zin":"douchen"},
		{"audience":"first","senha":"","zin":"Ons dak is kapot. Wij moeten..."},
		{"audience":"second","senha":"","zin":"het dak repareren"},
		{"audience":"first","senha":"","zin":"Orma heeft leuke buren. Ze gaat met haar buren..."},
		{"audience":"second","senha":"","zin":"op vakantie"},
		{"audience":"first","senha":"","zin":"Pablo gaat vaak met de trein. Hij gaat dan naar..."},
		{"audience":"second","senha":"","zin":"school"},
		{"audience":"first","senha":"","zin":"Pablo speelt gitaar. Hij oefent..."},
		{"audience":"second","senha":"","zin":"iedere dag"},
		{"audience":"first","senha":"","zin":"Pari gaat elke dag met de bus. Vandaag gaat ze..."},
		{"audience":"second","senha":"","zin":"fietsen"},
		{"audience":"first","senha":"","zin":"Pascal vindt zijn werk moeilijk. Hij wil..."},
		{"audience":"second","senha":"","zin":"het beter doen"},
		{"audience":"first","senha":"","zin":"Paul gaat vroeg naar bed. Hij moet morgen..."},
		{"audience":"second","senha":"","zin":"werken"},
		{"audience":"first","senha":"","zin":"Paul heeft honger. Zijn moeder geeft hem..."},
		{"audience":"second","senha":"","zin":"eten"},
		{"audience":"first","senha":"","zin":"Paul viert zijn verjaardag. Hij is..."},
		{"audience":"second","senha":"","zin":"jarig"},
		{"audience":"first","senha":"","zin":"Paula heeft een brief gekregen. De brief is van..."},
		{"audience":"second","senha":"","zin":"haar moeder"},
		{"audience":"first","senha":"","zin":"Pedro doet de lamp aan. Het is..."},
		{"audience":"second","senha":"","zin":"donker"},
		{"audience":"first","senha":"","zin":"Pedro woont op een boerderij. Hij heeft daar..."},
		{"audience":"second","senha":"","zin":"dieren"},
		{"audience":"first","senha":"","zin":"Peter maakt machines. Hij werkt vaak..."},
		{"audience":"second","senha":"","zin":"overdag"},
		{"audience":"first","senha":"","zin":"Peter speelt met zijn zoon. Ze zijn..."},
		{"audience":"second","senha":"","zin":"thuis"},
		{"audience":"first","senha":"","zin":"Philip fietst op de weg. De weg is..."},
		{"audience":"second","senha":"","zin":"druk"},
		{"audience":"first","senha":"","zin":"Philippa zit in de tuin. Ze zit ook vaak..."},
		{"audience":"second","senha":"","zin":"in huis"},
		{"audience":"first","senha":"","zin":"Pia woont naast een park. Ze gaat daar..."},
		{"audience":"second","senha":"","zin":"wandelen"},
		{"audience":"first","senha":"","zin":"Priya doet een opleiding. Later wordt ze..."},
		{"audience":"second","senha":"","zin":"dokter"}
	]
},{
	"title": "P.18",
	"content":[
		{"audience":"first","senha":"","zin":"Priya maakt saus. Haar dochters willen..."},
		{"audience":"second","senha":"","zin":"Spaghetti"},
		{"audience":"first","senha":"","zin":"Quito eet vandaag niet thuis. Hij eet..."},
		{"audience":"second","senha":"","zin":"bij vrienden"},
		{"audience":"first","senha":"","zin":"Rachel zingt vaak alleen. Soms zingt ze ook..."},
		{"audience":"second","senha":"","zin":"samen"},
		{"audience":"first","senha":"","zin":"Rafael heeft een telefoon. Hij belt elke dag met zijn..."},
		{"audience":"second","senha":"","zin":"moeder"},
		{"audience":"first","senha":"","zin":"Raheem heeft een fijn huis. Hij woont daar met..."},
		{"audience":"second","senha":"","zin":"zijn vriendin"},
		{"audience":"first","senha":"","zin":"Rahime heeft Nederlandse les. Ze vindt haar docent..."},
		{"audience":"second","senha":"","zin":"goed"},
		{"audience":"first","senha":"","zin":"Rasha werkt op een kantoor. Het kantoor is..."},
		{"audience":"second","senha":"","zin":"groot"},
		{"audience":"first","senha":"","zin":"Remi werkt op de markt. Hij verkoopt..."},
		{"audience":"second","senha":"","zin":"vis"},
		{"audience":"first","senha":"","zin":"Rhonda is haar sleutel kwijt. Nu moet ze..."},
		{"audience":"second","senha":"","zin":"hulp vragen"},
		{"audience":"first","senha":"","zin":"Rico eet vaak snoep. Snoep is slecht voor..."},
		{"audience":"second","senha":"","zin":"zijn tanden"},
		{"audience":"first","senha":"","zin":"Rico krijgt een prik. Hij is..."},
		{"audience":"second","senha":"","zin":"ziek"},
		{"audience":"first","senha":"","zin":"Rima en haar dochter zijn in de keuken. Haar dochter wil..."},
		{"audience":"second","senha":"","zin":"koken"},
		{"audience":"first","senha":"","zin":"Robin loopt snel naar school. Hij is..."},
		{"audience":"second","senha":"","zin":"te laat"},
		{"audience":"first","senha":"","zin":"Romeo werkt op een school. Hij geeft les aan..."},
		{"audience":"second","senha":"","zin":"kinderen"},
		{"audience":"first","senha":"","zin":"Roy wil zijn vriend spreken. Hij gaat..."},
		{"audience":"second","senha":"","zin":"voetballen"},
		{"audience":"first","senha":"","zin":"Ryan heeft weinig geld. Hij werkt..."},
		{"audience":"second","senha":"","zin":"niet"},
		{"audience":"first","senha":"","zin":"Ryan wil een film zien. Hij gaat naar..."},
		{"audience":"second","senha":"","zin":"de bioscoop"},
		{"audience":"first","senha":"","zin":"Sabir heeft een nieuwe baan. Hij werkt bij..."},
		{"audience":"second","senha":"","zin":"de politie"},
		{"audience":"first","senha":"","zin":"Saïd heeft vakantie. Hij gaat..."},
		{"audience":"second","senha":"","zin":"reizen"},
		{"audience":"first","senha":"","zin":"Saïd is te laat op zijn werk. Zijn baas is..."},
		{"audience":"second","senha":"","zin":"ongerust"}
	]
},{
	"title": "P.19",
	"content":[
		{"audience":"first","senha":"","zin":"Salih is bakker. Hij werkt meestal..."},
		{"audience":"second","senha":"","zin":"vroeg"},
		{"audience":"first","senha":"","zin":"Salim snijdt de uien. Zijn vrouw gaat..."},
		{"audience":"second","senha":"","zin":"koken"},
		{"audience":"first","senha":"","zin":"Sam loopt het lokaal uit. Hij gaat..."},
		{"audience":"second","senha":"","zin":"naar huis"},
		{"audience":"first","senha":"","zin":"Samir is te laat voor de trein. Hij moet nu..."},
		{"audience":"second","senha":"","zin":"rennen"},
		{"audience":"first","senha":"","zin":"Samira heeft een gesprek met haar baas. Ze praten over..."},
		{"audience":"second","senha":"","zin":"haar salaris"},
		{"audience":"first","senha":"","zin":"Samira gaat naar haar ouders. Ze gaan samen..."},
		{"audience":"second","senha":"","zin":"eten"},
		{"audience":"first","senha":"","zin":"Samira heeft pijn aan haar rug. Ze kan niet goed..."},
		{"audience":"second","senha":"","zin":"staan"},
		{"audience":"first","senha":"","zin":"Samuel heeft vandaag les. Hij gaat morgen..."},
		{"audience":"second","senha":"","zin":"slapen"},
		{"audience":"first","senha":"","zin":"Samuel praat met zijn baas. Hij vraagt..."},
		{"audience":"second","senha":"","zin":"hoe het gaat"},
		{"audience":"first","senha":"","zin":"Samuel vindt de pauze leuk. Hij gaat dan..."},
		{"audience":"second","senha":"","zin":"spelen"},
		{"audience":"first","senha":"","zin":"Sandra moet vandaag veel doen. Ze moet..."},
		{"audience":"second","senha":"","zin":"vroeg beginnen"},
		{"audience":"first","senha":"","zin":"Sanne kan niet goed koken. Het eten is..."},
		{"audience":"second","senha":"","zin":"vies"},
		{"audience":"first","senha":"","zin":"Sara praat met haar buurvrouw. Ze praten over..."},
		{"audience":"second","senha":"","zin":"het weer"},
		{"audience":"first","senha":"","zin":"Sarah is nooit ziek. Zij voelt zich altijd..."},
		{"audience":"second","senha":"","zin":"goed"},
		{"audience":"first","senha":"","zin":"Sari zoekt een cursusboek. Ze gaat naar..."},
		{"audience":"second","senha":"","zin":"school"},
		{"audience":"first","senha":"","zin":"Sasha eet niet altijd thuis. Ze gaat vaak naar..."},
		{"audience":"second","senha":"","zin":"haar ouders"},
		{"audience":"first","senha":"","zin":"Sasha gaat naar de bioscoop. Ze kijkt..."},
		{"audience":"second","senha":"","zin":"een film"},
		{"audience":"first","senha":"","zin":"Sasha heeft een hond. Ze heeft ook..."},
		{"audience":"second","senha":"","zin":"een kat"},
		{"audience":"first","senha":"","zin":"Savita gaat solliciteren. Ze wil..."},
		{"audience":"second","senha":"","zin":"werken"},
		{"audience":"first","senha":"","zin":"Scott doet een opleiding. Hij vindt leren..."},
		{"audience":"second","senha":"","zin":"leuk"}
	]
},{
	"title": "P.20",
	"content":[
		{"audience":"first","senha":"","zin":"Selim kan zijn broer niet bellen. Hij stuurt zijn broer een..."},
		{"audience":"second","senha":"","zin":"whatsapp bericht"},
		{"audience":"first","senha":"","zin":"Shaila draagt een rugzak naar school. In de rugzak zit..."},
		{"audience":"second","senha":"","zin":"een boek"},
		{"audience":"first","senha":"","zin":"Shanna heeft haar diploma. Ze is..."},
		{"audience":"second","senha":"","zin":"geslaagd"},
		{"audience":"first","senha":"","zin":"Shing heeft zijn arm gebroken. Hij mag niet..."},
		{"audience":"second","senha":"","zin":"werken"},
		{"audience":"first","senha":"","zin":"Shun wil niet eten. Hij wil liever..."},
		{"audience":"second","senha":"","zin":"drinken"},
		{"audience":"first","senha":"","zin":"Siham volgt een cursus. Ze leert..."},
		{"audience":"second","senha":"","zin":"Nederlands"},
		{"audience":"first","senha":"","zin":"Simon bouwt een huis. Het huis wordt.."},
		{"audience":"second","senha":"","zin":"groot"},
		{"audience":"first","senha":"","zin":"Simon wil leraar worden. Hij moet veel..."},
		{"audience":"second","senha":"","zin":"leren"},
		{"audience":"first","senha":"","zin":"Simone leest graag een krant. Ze koopt hem..."},
		{"audience":"second","senha":"","zin":"zaterdag"},
		{"audience":"first","senha":"","zin":"Sita geeft taart aan haar opa. Hij vindt dat..."},
		{"audience":"second","senha":"","zin":"lekker"},
		{"audience":"first","senha":"","zin":"Sjaak werkt in een fabriek. Daar werkt hij..."},
		{"audience":"second","senha":"","zin":"iedere dag"},
		{"audience":"first","senha":"","zin":"Sonia zit in de bus. Ze gaat naar..."},
		{"audience":"second","senha":"","zin":"huis"},
		{"audience":"first","senha":"","zin":"Sonya houdt van muziek. Ze luistert..."},
		{"audience":"second","senha":"","zin":"zouk"},
		{"audience":"first","senha":"","zin":"Sophia houdt van rijst. Ze kookt dat..."},
		{"audience":"second","senha":"","zin":"iedere dag"},
		{"audience":"first","senha":"","zin":"Sophie is vaak in het bos. Ze kijkt graag naar..."},
		{"audience":"second","senha":"","zin":"bomen"},
		{"audience":"first","senha":"","zin":"Sou eet graag maïs. Ze eet maïs meestal met..."},
		{"audience":"second","senha":"","zin":"boter"},
		{"audience":"first","senha":"","zin":"Souad koopt bananen op de markt. Ze koopt ook..."},
		{"audience":"second","senha":"","zin":"vis"},
		{"audience":"first","senha":"","zin":"Stanley wil een groter huis. Hij wil ook..."},
		{"audience":"second","senha":"","zin":"een garage"},
		{"audience":"first","senha":"","zin":"Stefan belt met zijn zus. Zijn zus is..."},
		{"audience":"second","senha":"","zin":"thuis"},
		{"audience":"first","senha":"","zin":"Stefana vindt wandelen leuk. Ze doet dat..."},
		{"audience":"second","senha":"","zin":"graag"}
	]
},{
	"title": "P.21",
	"content":[
		{"audience":"first","senha":"","zin":"Stephan moet sporten van de dokter. Hij gaat..."},
		{"audience":"second","senha":"","zin":"voetballen"},
		{"audience":"first","senha":"","zin":"Steven is in het ziekenhuis. Hij gaat morgen..."},
		{"audience":"second","senha":"","zin":"naar huis"},
		{"audience":"first","senha":"","zin":"Sven komt uit het ziekenhuis. Hij is..."},
		{"audience":"second","senha":"","zin":"beter"},
		{"audience":"first","senha":"","zin":"Sylvia is kapper. Ze moet vandaag veel..."},
		{"audience":"second","senha":"","zin":"knippen"},
		{"audience":"first","senha":"","zin":"Tamal moet remmen. Hij ziet een..."},
		{"audience":"second","senha":"","zin":"fiets"},
		{"audience":"first","senha":"","zin":"Tanya is bakker. Ze verkoopt..."},
		{"audience":"second","senha":"","zin":"brood"},
		{"audience":"first","senha":"","zin":"Tara wil een motor kopen. Een motor is..."},
		{"audience":"second","senha":"","zin":"mooi"},
		{"audience":"first","senha":"","zin":"Tara zoekt werk. Ze kijkt in..."},
		{"audience":"second","senha":"","zin":"de krant"},
		{"audience":"first","senha":"","zin":"Tariq eet alleen. Hij vindt dat..."},
		{"audience":"second","senha":"","zin":"rustig"},
		{"audience":"first","senha":"","zin":"Tess eet veel fruit. Fruit is..."},
		{"audience":"second","senha":"","zin":"gezond"},
		{"audience":"first","senha":"","zin":"Thirza wil later in het ziekenhuis werken. Ze moet eerst..."},
		{"audience":"second","senha":"","zin":"studeren"},
		{"audience":"first","senha":"","zin":"Thomas ligt in het ziekenhuis. Hij vindt dat..."},
		{"audience":"second","senha":"","zin":"rustig"},
		{"audience":"first","senha":"","zin":"Tim is jarig. Zijn zus geeft hem een..."},
		{"audience":"second","senha":"","zin":"cadeau"},
		{"audience":"first","senha":"","zin":"Tirza koopt een nieuw bed. Ze koopt ook..."},
		{"audience":"second","senha":"","zin":"kussens"},
		{"audience":"first","senha":"","zin":"Tony eet brood. Hij eet het brood met..."},
		{"audience":"second","senha":"","zin":"boter"},
		{"audience":"first","senha":"","zin":"Tuan zit op school. Hij heeft volgende week..."},
		{"audience":"second","senha":"","zin":"les"},
		{"audience":"first","senha":"","zin":"Veel mensen praten in de les. Nena vindt dat..."},
		{"audience":"second","senha":"","zin":"vervelend"},
		{"audience":"first","senha":"","zin":"Vera doet suiker in haar thee. Haar thee wordt zo..."},
		{"audience":"second","senha":"","zin":"zoet"},
		{"audience":"first","senha":"","zin":"Victor heeft een nieuw huis. Hij gaat morgen..."},
		{"audience":"second","senha":"","zin":"verhuizen"},
		{"audience":"first","senha":"","zin":"Wayan drinkt koffie met zijn buurman. Hij vindt dat..."},
		{"audience":"second","senha":"","zin":"gezellig"}
	]
},{
	"title": "P.22",
	"content":[
		{"audience":"first","senha":"","zin":"We gaan mijn broer ophalen. Hij heeft geen..."},
		{"audience":"second","senha":"","zin":"auto"},
		{"audience":"first","senha":"","zin":"Wij willen wat leuks doen. We gaan..."},
		{"audience":"second","senha":"","zin":"dansen"},
		{"audience":"first","senha":"","zin":"Wil je mijn huis zien? Ik woon hier..."},
		{"audience":"second","senha":"","zin":"samen met mijn vriend"},
		{"audience":"first","senha":"","zin":"Wil jij op mijn kinderen passen? Ik ga vanavond..."},
		{"audience":"second","senha":"","zin":"dansen"},
		{"audience":"first","senha":"","zin":"William neemt een drankje. Dat helpt tegen..."},
		{"audience":"second","senha":"","zin":"de dorst"},
		{"audience":"first","senha":"","zin":"Xuan is in de supermarkt. Ze wil..."},
		{"audience":"second","senha":"","zin":"brood"},
		{"audience":"first","senha":"","zin":"Yaira werkt bij een apotheek. Ze werkt daar..."},
		{"audience":"second","senha":"","zin":"iedere dag"},
		{"audience":"first","senha":"","zin":"Younes heeft veel vrienden. Hij gaat vaak met ze naar..."},
		{"audience":"second","senha":"","zin":"een café"},
		{"audience":"first","senha":"","zin":"Yun eet 's ochtends niet veel. Ze eet dan alleen..."},
		{"audience":"second","senha":"","zin":"fruit"},
		{"audience":"first","senha":"","zin":"Zarina moet de vis eerst schoonmaken. Daarna gaat ze hem..."},
		{"audience":"second","senha":"","zin":"bakken"},
		{"audience":"first","senha":"","zin":"Zina kookt met veel kruiden. Zo wordt haar eten..."},
		{"audience":"second","senha":"","zin":"lekker"},
		{"audience":"first","senha":"","zin":"Zola maakt het huis schoon. Ze doet dat..."},
		{"audience":"second","senha":"","zin":"goed"}
	]
}]
